deepnlp2024/__cli__.py
deepnlp2024/__init__.py
deepnlp2024/_version.py
deepnlp2024/conf/about/deepnlp2024.yaml
deepnlp2024/py.typed
deepnlp_2024-0.1.0.dist-info/LICENSE
deepnlp_2024-0.1.0.dist-info/METADATA
deepnlp_2024-0.1.0.dist-info/WHEEL
deepnlp_2024-0.1.0.dist-info/entry_points.txt
deepnlp_2024-0.1.0.dist-info/RECORD
