Metadata-Version: 2.1
Name: deepnlp-2024
Version: 0.1.0
Summary: Advanced deep learning techniques for natural language processing using the NVIDIA NeMo framework and DGX H100 server
Home-page: https://deepnlp2024.jeju.ai
License: CC-BY-4.0
Author: Young Joon Lee
Author-email: entelecheia@hotmail.com
Requires-Python: >=3.9,<3.13
Classifier: License :: Other/Proprietary License
Classifier: Programming Language :: Python :: 3
Classifier: Programming Language :: Python :: 3.9
Classifier: Programming Language :: Python :: 3.10
Classifier: Programming Language :: Python :: 3.11
Classifier: Programming Language :: Python :: 3.12
Requires-Dist: click (>=8.1.3,<9.0.0)
Requires-Dist: pyyaml (>=6.0.2,<7.0.0)
Project-URL: Repository, https://github.com/entelecheia/deepnlp-2024
